pylss/__init__.py
pylss/__main__.py
pylss-0.1.1.dist-info/LICENSE
pylss-0.1.1.dist-info/METADATA
pylss-0.1.1.dist-info/WHEEL
pylss-0.1.1.dist-info/top_level.txt
pylss-0.1.1.dist-info/RECORD
